naipng/__init__.py
naipng/__main__.py
naipng-1.0.0.post4.dist-info/LICENSE
naipng-1.0.0.post4.dist-info/METADATA
naipng-1.0.0.post4.dist-info/WHEEL
naipng-1.0.0.post4.dist-info/entry_points.txt
naipng-1.0.0.post4.dist-info/top_level.txt
naipng-1.0.0.post4.dist-info/RECORD
