Metadata-Version: 2.1
Name: naipng
Version: 1.0.0.post4
Summary: Library and command-line tool to read NovelAI data encoded in PNG files
Author: Eta
License: zlib/libpng License
Project-URL: Homepage, https://github.com/Eta0/naipng
Keywords: novelai,nai,png,cli
Classifier: Programming Language :: Python :: 3
Classifier: License :: OSI Approved :: zlib/libpng License
Classifier: Development Status :: 5 - Production/Stable
Classifier: Environment :: Console
Classifier: Operating System :: OS Independent
Classifier: Topic :: File Formats
Classifier: Intended Audience :: End Users/Desktop
Classifier: Intended Audience :: Developers
Requires-Python: >=3.7
License-File: LICENSE
